{
  "groups": [
    {
      "icon": "award",
      "title": "Grants & Awards",
      "items": [
        {
          "name": "World Bank / UGC HEAT Grant",
          "detail": "USD 80,000 · 2025 · top 10.2% nationally"
        },
        {
          "name": "AUT 3 Minute Thesis Competition",
          "detail": "Audience Choice Award · 2021"
        },
        {
          "name": "AUT Social Sciences Research Awards",
          "detail": "2015 & 2016"
        }
      ]
    },
    {
      "icon": "review",
      "title": "Peer Review Journal ",
      "items": [
        {
          "name": "Journal of the Royal Anthropological Institute (JRAI), UK",
          "detail": "Reviewer. JRAI"
        },
        {
          "name": "Research Institute of Asian Women, South Korea",
          "detail": "Reviewer. (SSCI & Scopus indexed)"
        },
        {
          "name": "Journal of Homosexuality",
          "detail": "Reviewer. Taylor & Francis"
        },
        {
          "name": "Journal of Contemporary South Asia",
          "detail": "Reviewer. Routledge"
        }
      ]
    },
    {
      "icon": "leadership",
      "title": "Leadership & Service",
      "items": [
        {
          "name": "Hall Provost",
          "detail": "Begum Sufia Kamal Hall · 2025–Present"
        },
        {
          "name": "Trustee Board Member",
          "detail": "National Child Welfare Trust · 2024–Present"
        },
        {
          "name": "Reviewer",
          "detail": "National Youth Development Institute · 2024–Present"
        },
        {
          "name": "International Coordinator",
          "detail": "IMRF Bangladesh"
        },
        {
          "name": "Student Adviser, Department of Anthropology",
          "detail": "Jahangirnagar University. 2024 – Present"
        },
        {
          "name": "Election Committee Member, JUCSU",
          "detail": "Jahangirnagar University. 2024 – 2025"
        },
        {
          "name": "Deputy Director, Teacher-Student Centre (TSC)",
          "detail": "Jahangirnagar University. 2024 – 2025"
        }
      ]
    },
    {
      "icon": "membership",
      "title": "Memberships",
      "items": [
        {
          "name": "World Anthropology Union (WAU)"
        },
        {
          "name": "IUAES",
          "detail": "International Union of Anthropological and Ethnological Sciences (IUAES)"
        },
        {
          "name": "Sex Tech Lab",
          "detail": "The New School, New York"
        },
        {
          "name": "Canada–Bangladesh Social Justice Alliance"
        },
        {
          "name": "Kapaeeng Foundation"
        },
        {
          "name": "IMRF Bangladesh"
        },
        {
          "name": "Duke of Edinburgh's Award Leader Foundation"
        },
        {
          "name": "The World School of Bangladesh"
        }
      ]
    }
  ]
}